MANIFEST.in
README.rst
setup.cfg
setup.py
bin/eow
eow/__init__.py
eow/__main__.py
eow.egg-info/PKG-INFO
eow.egg-info/SOURCES.txt
eow.egg-info/dependency_links.txt
eow.egg-info/not-zip-safe
eow.egg-info/requires.txt
eow.egg-info/top_level.txt
eow/static/jquery-2.1.4.js
eow/static/main.js
eow/static/style.css
eow/static/codemirror/addon/comment/comment.js
eow/static/codemirror/addon/comment/continuecomment.js
eow/static/codemirror/addon/dialog/dialog.css
eow/static/codemirror/addon/dialog/dialog.js
eow/static/codemirror/addon/display/fullscreen.css
eow/static/codemirror/addon/display/fullscreen.js
eow/static/codemirror/addon/display/panel.js
eow/static/codemirror/addon/display/placeholder.js
eow/static/codemirror/addon/display/rulers.js
eow/static/codemirror/addon/edit/closebrackets.js
eow/static/codemirror/addon/edit/closetag.js
eow/static/codemirror/addon/edit/continuelist.js
eow/static/codemirror/addon/edit/matchbrackets.js
eow/static/codemirror/addon/edit/matchtags.js
eow/static/codemirror/addon/edit/trailingspace.js
eow/static/codemirror/addon/fold/brace-fold.js
eow/static/codemirror/addon/fold/comment-fold.js
eow/static/codemirror/addon/fold/foldcode.js
eow/static/codemirror/addon/fold/foldgutter.css
eow/static/codemirror/addon/fold/foldgutter.js
eow/static/codemirror/addon/fold/indent-fold.js
eow/static/codemirror/addon/fold/markdown-fold.js
eow/static/codemirror/addon/fold/xml-fold.js
eow/static/codemirror/addon/hint/anyword-hint.js
eow/static/codemirror/addon/hint/css-hint.js
eow/static/codemirror/addon/hint/html-hint.js
eow/static/codemirror/addon/hint/javascript-hint.js
eow/static/codemirror/addon/hint/show-hint.css
eow/static/codemirror/addon/hint/show-hint.js
eow/static/codemirror/addon/hint/sql-hint.js
eow/static/codemirror/addon/hint/xml-hint.js
eow/static/codemirror/addon/lint/coffeescript-lint.js
eow/static/codemirror/addon/lint/css-lint.js
eow/static/codemirror/addon/lint/javascript-lint.js
eow/static/codemirror/addon/lint/json-lint.js
eow/static/codemirror/addon/lint/lint.css
eow/static/codemirror/addon/lint/lint.js
eow/static/codemirror/addon/lint/yaml-lint.js
eow/static/codemirror/addon/merge/merge.css
