Metadata-Version: 1.0
Name: eow
Version: 2015.1.1
Summary: Edit local files in CodeMirror
Home-page: UNKNOWN
Author: Andreas Kloeckner
Author-email: inform@tiker.net
License: MIT
Platform: UNKNOWN
